{
  "version": 1,
  "width": 80,
  "height": 24,
  "duration": 115.631828,
  "command": "/bin/bash",
  "title": "",
  "env": {
    "TERM": "xterm-256color",
    "SHELL": "/bin/bash"
  },
  "stdout": [
    [
      0.066491,
      "\u001b]0;rhack@bigoook:/tmp/plt\u0007"
    ],
    [
      0.000072,
      "\u001b[?1034h"
    ],
    [
      0.000015,
      "[rhack@bigoook plt]$ "
    ],
    [
      0.409662,
      "n"
    ],
    [
      0.071708,
      "a"
    ],
    [
      0.112241,
      "n"
    ],
    [
      0.272141,
      "o"
    ],
    [
      0.111812,
      " "
    ],
    [
      0.135975,
      "m"
    ],
    [
      0.064203,
      "e"
    ],
    [
      0.143930,
      "s"
    ],
    [
      0.128057,
      "s"
    ],
    [
      0.079810,
      "."
    ],
    [
      0.095979,
      "c"
    ],
    [
      0.449220,
      "\r\n"
    ],
    [
      0.003052,
      "\u001b[?1049h\u001b[1;24r\u001b(B\u001b[m\u001b[4l\u001b[?7h\u001b[?12l\u001b[?25h\u001b[?1h\u001b=\u001b[?1h\u001b=\u001b[?1h\u001b=\u001b[39;49m\u001b[39;49m\u001b(B\u001b[m\u001b[H\u001b[2J\u001b(B\u001b[0;7m  GNU nano 2.3.2               File: mess.c                                     \u001b[22;35H[ New File ]\r\u001b[23d^G\u001b(B\u001b[m Get Help  \u001b(B\u001b[0;7m^O\u001b(B\u001b[m WriteOut  \u001b(B\u001b[0;7m^R\u001b(B\u001b[m Read File \u001b(B\u001b[0;7m^Y\u001b(B\u001b[m Prev Page \u001b(B\u001b[0;7m^K\u001b(B\u001b[m Cut Text  \u001b(B\u001b[0;7m^C\u001b(B\u001b[m Cur Pos\r\u001b[24d\u001b(B\u001b[0;7m^X\u001b(B\u001b[m Exit\u001b[14G\u001b(B\u001b[0;7m^J\u001b(B\u001b[m Justify   \u001b(B\u001b[0;7m^W\u001b(B\u001b[m Where Is  \u001b(B\u001b[0;7m^V\u001b(B\u001b[m Next Page \u001b(B\u001b[0;7m^U\u001b(B\u001b[m UnCut Text\u001b(B\u001b[0;7m^T\u001b(B\u001b[m To Spell\r\u001b[3d"
    ],
    [
      1.028190,
      "\u001b[1;71H\u001b(B\u001b[0;7mModified\r\u001b[3d\u001b(B\u001b[m#"
    ],
    [
      0.263874,
      "i"
    ],
    [
      0.063982,
      "n"
    ],
    [
      0.111962,
      "c"
    ],
    [
      0.111900,
      "l"
    ],
    [
      0.136066,
      "u"
    ],
    [
      0.111834,
      "d"
    ],
    [
      0.152092,
      "e"
    ],
    [
      0.087640,
      " "
    ],
    [
      0.088077,
      "\u003c"
    ],
    [
      0.184375,
      "s"
    ],
    [
      0.304008,
      "t"
    ],
    [
      0.392024,
      "d"
    ],
    [
      0.311982,
      "l"
    ],
    [
      0.072006,
      "i"
    ],
    [
      0.119847,
      "b"
    ],
    [
      0.160195,
      "."
    ],
    [
      0.335993,
      "h"
    ],
    [
      0.303943,
      "\u003e"
    ],
    [
      0.544362,
      "\r\u001b[4d"
    ],
    [
      0.279670,
      "#"
    ],
    [
      0.800071,
      "i"
    ],
    [
      0.071975,
      "n"
    ],
    [
      0.104301,
      "c"
    ],
    [
      0.095561,
      "l"
    ],
    [
      0.128164,
      "u\r\u001b[22d\u001b[K\u001b[4;7H"
    ],
    [
      0.071850,
      "d"
    ],
    [
      0.159844,
      "e"
    ],
    [
      0.080166,
      " "
    ],
    [
      0.127913,
      "\u003c"
    ],
    [
      0.240014,
      "s"
    ],
    [
      0.576498,
      "t"
    ],
    [
      0.287626,
      "d"
    ],
    [
      0.263734,
      "i"
    ],
    [
      0.136070,
      "o"
    ],
    [
      0.216119,
      "."
    ],
    [
      0.288252,
      "h"
    ],
    [
      0.271811,
      "\u003e"
    ],
    [
      0.424442,
      "\r\u001b[5d"
    ],
    [
      0.455991,
      "\u001b[6d"
    ],
    [
      0.351495,
      "i"
    ],
    [
      0.071967,
      "n"
    ],
    [
      0.064207,
      "t"
    ],
    [
      0.488108,
      " "
    ],
    [
      0.111720,
      "m"
    ],
    [
      0.071970,
      "a"
    ],
    [
      0.119995,
      "i"
    ],
    [
      0.071936,
      "n"
    ],
    [
      0.424253,
      "("
    ],
    [
      0.391962,
      ")"
    ],
    [
      0.264289,
      "\r\u001b[7d"
    ],
    [
      0.279736,
      "{"
    ],
    [
      0.007877,
      "}"
    ],
    [
      0.528036,
      "\u0008 \u0008"
    ],
    [
      0.256484,
      "\r\u001b[8d"
    ],
    [
      0.159797,
      "\u001b[9d"
    ],
    [
      0.367747,
      "}"
    ],
    [
      0.191705,
      "\r\u001b[A"
    ],
    [
      0.328257,
      "\u001b[8;9H"
    ],
    [
      0.736087,
      "p"
    ],
    [
      0.143904,
      "r"
    ],
    [
      0.071921,
      "i"
    ],
    [
      0.071901,
      "n"
    ],
    [
      0.056098,
      "t"
    ],
    [
      0.159968,
      "f"
    ],
    [
      0.567980,
      "("
    ],
    [
      0.384142,
      "\""
    ],
    [
      1.039961,
      "c"
    ],
    [
      0.104006,
      "a"
    ],
    [
      0.168116,
      "t"
    ],
    [
      0.111570,
      " "
    ],
    [
      0.104195,
      "m"
    ],
    [
      0.055990,
      "e"
    ],
    [
      0.152183,
      "s"
    ],
    [
      0.127886,
      "s"
    ],
    [
      0.152203,
      "."
    ],
    [
      0.584090,
      "c"
    ],
    [
      1.032111,
      "\""
    ],
    [
      0.455611,
      ")"
    ],
    [
      0.280510,
      ";"
    ],
    [
      0.376108,
      "\u001b7\u001b[9;22r\u001b8\r\u001b[9d\u001bM\u001b[1;24r\u001b[9;1H"
    ],
    [
      0.607533,
      "\u001b[9;9H"
    ],
    [
      0.264204,
      "s"
    ],
    [
      0.144137,
      "y"
    ],
    [
      0.071617,
      "s"
    ],
    [
      0.175987,
      "t"
    ],
    [
      0.079847,
      "e"
    ],
    [
      0.135976,
      "m"
    ],
    [
      0.600022,
      "("
    ],
    [
      1.328162,
      "\""
    ],
    [
      0.567764,
      "h"
    ],
    [
      0.072665,
      "e"
    ],
    [
      0.159632,
      "l"
    ],
    [
      0.127927,
      "l"
    ],
    [
      0.159755,
      "o"
    ],
    [
      1.184292,
      "\""
    ],
    [
      0.520336,
      ")"
    ],
    [
      0.552216,
      ";"
    ],
    [
      0.759410,
      "\r\u001b[22d\u001b(B\u001b[0;7mSave modified buffer (ANSWERING \"No\" WILL DESTROY CHANGES) ?                    \u001b[23;1H Y\u001b(B\u001b[m Yes\u001b[K\r\u001b[24d\u001b(B\u001b[0;7m N\u001b(B\u001b[m No  \u001b[14G   \u001b(B\u001b[0;7m^C\u001b(B\u001b[m Cancel\u001b[K\u001b[22;62H"
    ],
    [
      1.816235,
      "\r\u001b(B\u001b[0;7mFile Name to Write: mess.c                                  \r\u001b[23d^G\u001b(B\u001b[m Get Help\u001b[23;21H\u001b(B\u001b[0;7mM-D\u001b(B\u001b[m DOS Format\t\u001b(B\u001b[0;7mM-A\u001b(B\u001b[m Append\u001b[23;61H\u001b(B\u001b[0;7mM-B\u001b(B\u001b[m Backup File\r\u001b[24d\u001b(B\u001b[0;7m^C\u001b(B\u001b[m Cancel\t    \u001b(B\u001b[0;7mM-M\u001b(B\u001b[m Mac Format\t\u001b(B\u001b[0;7mM-P\u001b(B\u001b[m Prepend\u001b[22;27H"
    ],
    [
      0.826743,
      "\r\u001b[23d\u001b[39;49m\u001b(B\u001b[m\u001b[J\u001b[1;71H\u001b(B\u001b[0;7m        \u001b[22;31H\u001b(B\u001b[m\u001b[1K \u001b(B\u001b[0;7m[ Wrote 8 lines ]\u001b(B\u001b[m\u001b[K\u001b[24;80H\u001b[24;1H\u001b[?1049l\r\u001b[?1l\u001b\u003e"
    ],
    [
      0.000325,
      "\u001b]0;rhack@bigoook:/tmp/plt\u0007[rhack@bigoook plt]$ "
    ],
    [
      0.428631,
      "m"
    ],
    [
      0.104134,
      "a"
    ],
    [
      0.087837,
      "k"
    ],
    [
      0.064027,
      "e"
    ],
    [
      0.120038,
      " "
    ],
    [
      0.103735,
      "m"
    ],
    [
      0.096273,
      "e"
    ],
    [
      0.152041,
      "s"
    ],
    [
      0.127741,
      "s"
    ],
    [
      0.473181,
      "\r\n"
    ],
    [
      0.003070,
      "cc     mess.c   -o mess\r\n"
    ],
    [
      0.057350,
      "\u001b]0;rhack@bigoook:/tmp/plt\u0007[rhack@bigoook plt]$ "
    ],
    [
      1.946562,
      "."
    ],
    [
      0.055779,
      "/"
    ],
    [
      0.224270,
      "m"
    ],
    [
      0.047782,
      "e"
    ],
    [
      0.160105,
      "s"
    ],
    [
      0.143964,
      "s"
    ],
    [
      0.576099,
      ";"
    ],
    [
      0.103969,
      " "
    ],
    [
      0.143947,
      "e"
    ],
    [
      0.151949,
      "c"
    ],
    [
      0.079958,
      "h"
    ],
    [
      0.048185,
      "o"
    ],
    [
      0.167905,
      " "
    ],
    [
      0.295976,
      "\""
    ],
    [
      0.736302,
      "\\"
    ],
    [
      0.559783,
      "n"
    ],
    [
      0.367995,
      "\""
    ],
    [
      0.521119,
      "\r\n"
    ],
    [
      0.003146,
      "sh: hello: command not found\r\n"
    ],
    [
      0.000462,
      "cat mess.c"
    ],
    [
      0.000495,
      "\\n\r\n\u001b]0;rhack@bigoook:/tmp/plt\u0007[rhack@bigoook plt]$ "
    ],
    [
      2.634718,
      "g"
    ],
    [
      0.120065,
      "d"
    ],
    [
      0.207985,
      "b"
    ],
    [
      0.127831,
      " "
    ],
    [
      0.136097,
      "-"
    ],
    [
      0.127951,
      "q"
    ],
    [
      0.256313,
      " "
    ],
    [
      0.327944,
      "h"
    ],
    [
      0.112058,
      "e"
    ],
    [
      0.487997,
      "\u0008\u001b[K"
    ],
    [
      0.127607,
      "\u0008\u001b[K"
    ],
    [
      0.424306,
      "."
    ],
    [
      0.087938,
      "/"
    ],
    [
      0.224020,
      "m"
    ],
    [
      0.087891,
      "e"
    ],
    [
      0.152022,
      "s"
    ],
    [
      0.120071,
      "s"
    ],
    [
      0.353214,
      "\r\n"
    ],
    [
      0.038697,
      "\u001b[?1034h"
    ],
    [
      0.000930,
      "Reading symbols from ./mess..."
    ],
    [
      0.000157,
      "(no debugging symbols found)...done."
    ],
    [
      0.000004,
      "\r\n"
    ],
    [
      0.000140,
      "(gdb) "
    ],
    [
      1.390971,
      "s"
    ],
    [
      0.063889,
      "e"
    ],
    [
      0.151942,
      "t"
    ],
    [
      0.120144,
      " "
    ],
    [
      0.160007,
      "e"
    ],
    [
      0.175850,
      "n"
    ],
    [
      0.144081,
      "v"
    ],
    [
      0.159989,
      "i"
    ],
    [
      0.136256,
      "ronment "
    ],
    [
      0.927730,
      "L"
    ],
    [
      0.103876,
      "D"
    ],
    [
      0.320138,
      "_"
    ],
    [
      0.135982,
      "B"
    ],
    [
      0.152018,
      "I"
    ],
    [
      0.079983,
      "N"
    ],
    [
      0.056030,
      "D"
    ],
    [
      0.775939,
      "_"
    ],
    [
      0.272157,
      "N"
    ],
    [
      0.096045,
      "O"
    ],
    [
      0.079819,
      "W"
    ],
    [
      0.352078,
      "="
    ],
    [
      0.143887,
      "1"
    ],
    [
      0.479997,
      "\r\n(gdb) "
    ],
    [
      1.632041,
      "s"
    ],
    [
      0.168008,
      "t"
    ],
    [
      0.096022,
      "a"
    ],
    [
      0.119942,
      "r"
    ],
    [
      0.119989,
      "t"
    ],
    [
      0.640686,
      "\r\nTemporary breakpoint 1 at 0x400584\r\nStarting program: /tmp/plt/mess \r\n"
    ],
    [
      0.044063,
      "\r\n"
    ],
    [
      0.000031,
      "Temporary breakpoint 1, 0x0000000000400584 in main ()"
    ],
    [
      0.000005,
      "\r\n"
    ],
    [
      0.000110,
      "(gdb) "
    ],
    [
      1.203002,
      "d"
    ],
    [
      0.127755,
      "i"
    ],
    [
      0.352839,
      "s"
    ],
    [
      0.183527,
      "a"
    ],
    [
      0.191971,
      "s"
    ],
    [
      0.200212,
      "semble "
    ],
    [
      0.351872,
      "m"
    ],
    [
      0.103900,
      "a"
    ],
    [
      0.063918,
      "i"
    ],
    [
      0.063726,
      "n"
    ],
    [
      0.696924,
      "\r\n"
    ],
    [
      0.016987,
      "Dump of assembler code for function main:\r\n"
    ],
    [
      0.000129,
      "   0x0000000000400580 \u003c+0\u003e:\tpush   %rbp\r\n"
    ],
    [
      0.000033,
      "   0x0000000000400581 \u003c+1\u003e:\t"
    ],
    [
      0.000007,
      "mov    %rsp,%rbp\r\n"
    ],
    [
      0.000031,
      "=\u003e 0x0000000000400584 \u003c+4\u003e:\t"
    ],
    [
      0.000010,
      "mov    $0x400630,%edi\r\n"
    ],
    [
      0.000020,
      "   0x0000000000400589 \u003c+9\u003e:"
    ],
    [
      0.000006,
      "\tmov    $0x0,%eax\r\n"
    ],
    [
      0.000036,
      "   0x000000000040058e \u003c+14\u003e:\t"
    ],
    [
      0.000006,
      "callq  0x400460 \u003cprintf@plt\u003e\r\n"
    ],
    [
      0.000029,
      "   0x0000000000400593 \u003c+19\u003e:\tmov    $0x40063b,%edi"
    ],
    [
      0.000005,
      "\r\n"
    ],
    [
      0.000028,
      "   0x0000000000400598 \u003c+24\u003e:\t"
    ],
    [
      0.000006,
      "callq  0x400450 \u003csystem@plt\u003e\r\n"
    ],
    [
      0.000028,
      "   0x000000000040059d \u003c+29\u003e:\t"
    ],
    [
      0.000007,
      "pop    %rbp\r\n"
    ],
    [
      0.000016,
      "   0x000000000040059e \u003c+30\u003e:\t"
    ],
    [
      0.000005,
      "retq   \r\n"
    ],
    [
      0.000013,
      "End of assembler dump."
    ],
    [
      0.000006,
      "\r\n"
    ],
    [
      0.000094,
      "(gdb) "
    ],
    [
      0.613865,
      "x"
    ],
    [
      0.127793,
      "/"
    ],
    [
      0.880334,
      "1"
    ],
    [
      0.096331,
      "0"
    ],
    [
      0.327848,
      "i"
    ],
    [
      0.135840,
      " "
    ],
    [
      2.391327,
      "0x400450"
    ],
    [
      0.929500,
      "\r\n   0x400450 \u003csystem@plt\u003e:\t\r\n    jmpq   *0x200bc2(%rip)        # 0x601018 \u003csystem@got.plt\u003e\r\n   0x400456 \u003csystem@plt+6\u003e:\tpushq  $0x0\r\n   0x40045b \u003csystem@plt+11\u003e:\tjmpq   0x400440\r\n   0x400460 \u003cprintf@plt\u003e:\t\r\n    jmpq   *0x200bba(%rip)        # 0x601020 \u003cprintf@got.plt\u003e\r\n   0x400466 \u003cprintf@plt+6\u003e:\tpushq  $0x1\r\n   0x40046b \u003cprintf@plt+11\u003e:\tjmpq   0x400440\r\n   0x400470 \u003c__libc_start_main@plt\u003e:\t\r\n    jmpq   *0x200bb2(%rip)        # 0x601028 \u003c__libc_start_main@got.plt\u003e\r\n   0x400476 \u003c__libc_start_main@plt+6\u003e:\tpushq  $0x2\r\n   0x40047b \u003c__libc_start_main@plt+11\u003e:\tjmpq   0x400440\r\n   0x400480 \u003c__gmon_start__@plt\u003e:\t\r\n    jmpq   *0x200baa(%rip)        # 0x601030 \u003c__gmon_start__@got.plt\u003e\r\n(gdb) "
    ],
    [
      3.199007,
      "x"
    ],
    [
      0.560139,
      "/"
    ],
    [
      0.263980,
      "1"
    ],
    [
      0.759983,
      "a"
    ],
    [
      0.176049,
      " "
    ],
    [
      0.775625,
      "0x601018"
    ],
    [
      0.063723,
      "0x601018"
    ],
    [
      1.152783,
      "\r\u001b[C\u001b[C\u001b[C\u001b[C\u001b[C\u001b[C\u001b[C\u001b[C\u001b[C\u001b[C\u001b[C\u001b[K"
    ],
    [
      0.766696,
      "0x601018"
    ],
    [
      0.691583,
      "\r\n0x601018 \u003csystem@got.plt\u003e:\t0x3b65a42880 \u003c__libc_system\u003e\r\n(gdb) "
    ],
    [
      0.493633,
      "x"
    ],
    [
      0.160015,
      "/"
    ],
    [
      0.359892,
      "1"
    ],
    [
      1.319686,
      "a"
    ],
    [
      2.040444,
      " "
    ],
    [
      1.398906,
      "0x601020"
    ],
    [
      0.937841,
      "\r\n0x601020 \u003cprintf@got.plt\u003e:\t0x3b65a51a50 \u003c__printf\u003e\r\n(gdb) "
    ],
    [
      0.399282,
      "s"
    ],
    [
      0.095989,
      "e"
    ],
    [
      0.159919,
      "t"
    ],
    [
      0.127777,
      " "
    ],
    [
      2.040008,
      "*"
    ],
    [
      2.719927,
      "0x601018"
    ],
    [
      0.407860,
      " "
    ],
    [
      0.776343,
      "="
    ],
    [
      0.120120,
      " "
    ],
    [
      2.167187,
      "0x3b65a51a50"
    ],
    [
      0.960939,
      "\r\n(gdb) "
    ],
    [
      0.295418,
      "s"
    ],
    [
      0.064017,
      "e"
    ],
    [
      0.192499,
      "t"
    ],
    [
      0.087885,
      " "
    ],
    [
      0.207591,
      "*"
    ],
    [
      3.887691,
      "0x601020"
    ],
    [
      0.640804,
      " "
    ],
    [
      0.352332,
      "="
    ],
    [
      0.096020,
      " "
    ],
    [
      2.238837,
      "0x3b65a42880"
    ],
    [
      0.945185,
      "\r\n(gdb) "
    ],
    [
      0.959892,
      "c"
    ],
    [
      0.055963,
      "o"
    ],
    [
      0.096062,
      "n"
    ],
    [
      0.167759,
      "t"
    ],
    [
      0.079757,
      "i"
    ],
    [
      0.112215,
      "nue "
    ],
    [
      0.312313,
      "\r\nContinuing.\r\n"
    ],
    [
      0.000998,
      "Detaching after fork from child process 11796.\r\n"
    ],
    [
      0.002523,
      "#include \u003cstdlib.h\u003e\r\n#include \u003cstdio.h\u003e\r\n\r\nint main()\r\n{\r\n\tprintf(\"cat mess.c\");\r\n\tsystem(\"hello\");\r\n}\r\n"
    ],
    [
      0.000300,
      "hello"
    ],
    [
      0.000104,
      "[Inferior 1 (process 11718) exited with code 05]"
    ],
    [
      0.000005,
      "\r\n"
    ],
    [
      0.000205,
      "(gdb) "
    ],
    [
      4.321178,
      "quit\r\n"
    ],
    [
      0.000330,
      "\u001b]0;rhack@bigoook:/tmp/plt\u0007[rhack@bigoook plt]$ "
    ],
    [
      0.410062,
      "e"
    ],
    [
      0.415831,
      "c"
    ],
    [
      0.128345,
      "h"
    ],
    [
      0.055661,
      "o"
    ],
    [
      0.119979,
      " "
    ],
    [
      0.288167,
      "\""
    ],
    [
      2.199963,
      "A"
    ],
    [
      0.175909,
      "n"
    ],
    [
      0.120215,
      "d"
    ],
    [
      0.127878,
      " "
    ],
    [
      0.215910,
      "t"
    ],
    [
      0.111833,
      "h"
    ],
    [
      0.056116,
      "i"
    ],
    [
      0.104092,
      "s"
    ],
    [
      0.151940,
      " "
    ],
    [
      0.344041,
      "i"
    ],
    [
      0.160136,
      "s"
    ],
    [
      0.239924,
      " "
    ],
    [
      0.271927,
      "i"
    ],
    [
      0.104025,
      "t"
    ],
    [
      0.239974,
      "."
    ],
    [
      0.152350,
      "."
    ],
    [
      0.127653,
      "."
    ],
    [
      0.408425,
      "\""
    ],
    [
      0.968464,
      "\r\nAnd this is it...\r\n\u001b]0;rhack@bigoook:/tmp/plt\u0007[rhack@bigoook plt]$ "
    ],
    [
      1.298563,
      "exit\r\n"
    ]
  ]
}